benchdas/__init__.py
benchdas/benchmarking.py
benchdas-0.4.0.dist-info/LICENSE
benchdas-0.4.0.dist-info/METADATA
benchdas-0.4.0.dist-info/WHEEL
benchdas-0.4.0.dist-info/RECORD
